<annotation>
	<folder>Img_cap_aume</folder>
	<filename>1017.jpg</filename>
	<path>C:\labelm\Retinanet_tutorial\Img_cap_aume\1017.jpg</path>
	<source>
		<database>Unknown</database>
	</source>
	<size>
		<width>720</width>
		<height>720</height>
		<depth>3</depth>
	</size>
	<segmented>0</segmented>
	<object>
		<name>F</name>
		<pose>Unspecified</pose>
		<truncated>0</truncated>
		<difficult>0</difficult>
		<bndbox>
			<xmin>611</xmin>
			<ymin>131</ymin>
			<xmax>676</xmax>
			<ymax>194</ymax>
		</bndbox>
	</object>
	<object>
		<name>F</name>
		<pose>Unspecified</pose>
		<truncated>0</truncated>
		<difficult>0</difficult>
		<bndbox>
			<xmin>212</xmin>
			<ymin>163</ymin>
			<xmax>268</xmax>
			<ymax>209</ymax>
		</bndbox>
	</object>
	<object>
		<name>F</name>
		<pose>Unspecified</pose>
		<truncated>0</truncated>
		<difficult>0</difficult>
		<bndbox>
			<xmin>122</xmin>
			<ymin>153</ymin>
			<xmax>177</xmax>
			<ymax>200</ymax>
		</bndbox>
	</object>
	<object>
		<name>F</name>
		<pose>Unspecified</pose>
		<truncated>0</truncated>
		<difficult>0</difficult>
		<bndbox>
			<xmin>27</xmin>
			<ymin>152</ymin>
			<xmax>73</xmax>
			<ymax>194</ymax>
		</bndbox>
	</object>
	<object>
		<name>F</name>
		<pose>Unspecified</pose>
		<truncated>0</truncated>
		<difficult>0</difficult>
		<bndbox>
			<xmin>587</xmin>
			<ymin>638</ymin>
			<xmax>653</xmax>
			<ymax>702</ymax>
		</bndbox>
	</object>
	<object>
		<name>F</name>
		<pose>Unspecified</pose>
		<truncated>0</truncated>
		<difficult>0</difficult>
		<bndbox>
			<xmin>659</xmin>
			<ymin>412</ymin>
			<xmax>692</xmax>
			<ymax>451</ymax>
		</bndbox>
	</object>
	<object>
		<name>F</name>
		<pose>Unspecified</pose>
		<truncated>0</truncated>
		<difficult>0</difficult>
		<bndbox>
			<xmin>33</xmin>
			<ymin>39</ymin>
			<xmax>111</xmax>
			<ymax>110</ymax>
		</bndbox>
	</object>
</annotation>
