<annotation>
	<folder>Img_cap_aume</folder>
	<filename>1053.jpg</filename>
	<path>C:\labelm\Retinanet_tutorial\Img_cap_aume\1053.jpg</path>
	<source>
		<database>Unknown</database>
	</source>
	<size>
		<width>720</width>
		<height>720</height>
		<depth>3</depth>
	</size>
	<segmented>0</segmented>
	<object>
		<name>P</name>
		<pose>Unspecified</pose>
		<truncated>0</truncated>
		<difficult>0</difficult>
		<bndbox>
			<xmin>160</xmin>
			<ymin>261</ymin>
			<xmax>193</xmax>
			<ymax>336</ymax>
		</bndbox>
	</object>
	<object>
		<name>P</name>
		<pose>Unspecified</pose>
		<truncated>0</truncated>
		<difficult>0</difficult>
		<bndbox>
			<xmin>305</xmin>
			<ymin>261</ymin>
			<xmax>338</xmax>
			<ymax>334</ymax>
		</bndbox>
	</object>
	<object>
		<name>P</name>
		<pose>Unspecified</pose>
		<truncated>0</truncated>
		<difficult>0</difficult>
		<bndbox>
			<xmin>344</xmin>
			<ymin>339</ymin>
			<xmax>376</xmax>
			<ymax>410</ymax>
		</bndbox>
	</object>
	<object>
		<name>P</name>
		<pose>Unspecified</pose>
		<truncated>0</truncated>
		<difficult>0</difficult>
		<bndbox>
			<xmin>188</xmin>
			<ymin>636</ymin>
			<xmax>255</xmax>
			<ymax>673</ymax>
		</bndbox>
	</object>
	<object>
		<name>P</name>
		<pose>Unspecified</pose>
		<truncated>0</truncated>
		<difficult>0</difficult>
		<bndbox>
			<xmin>341</xmin>
			<ymin>631</ymin>
			<xmax>408</xmax>
			<ymax>671</ymax>
		</bndbox>
	</object>
	<object>
		<name>P</name>
		<pose>Unspecified</pose>
		<truncated>0</truncated>
		<difficult>0</difficult>
		<bndbox>
			<xmin>457</xmin>
			<ymin>629</ymin>
			<xmax>521</xmax>
			<ymax>663</ymax>
		</bndbox>
	</object>
	<object>
		<name>P</name>
		<pose>Unspecified</pose>
		<truncated>0</truncated>
		<difficult>0</difficult>
		<bndbox>
			<xmin>650</xmin>
			<ymin>663</ymin>
			<xmax>707</xmax>
			<ymax>694</ymax>
		</bndbox>
	</object>
	<object>
		<name>F</name>
		<pose>Unspecified</pose>
		<truncated>0</truncated>
		<difficult>0</difficult>
		<bndbox>
			<xmin>344</xmin>
			<ymin>263</ymin>
			<xmax>372</xmax>
			<ymax>292</ymax>
		</bndbox>
	</object>
	<object>
		<name>F</name>
		<pose>Unspecified</pose>
		<truncated>0</truncated>
		<difficult>0</difficult>
		<bndbox>
			<xmin>305</xmin>
			<ymin>417</ymin>
			<xmax>337</xmax>
			<ymax>450</ymax>
		</bndbox>
	</object>
	<object>
		<name>F</name>
		<pose>Unspecified</pose>
		<truncated>0</truncated>
		<difficult>0</difficult>
		<bndbox>
			<xmin>161</xmin>
			<ymin>422</ymin>
			<xmax>191</xmax>
			<ymax>452</ymax>
		</bndbox>
	</object>
	<object>
		<name>F</name>
		<pose>Unspecified</pose>
		<truncated>0</truncated>
		<difficult>0</difficult>
		<bndbox>
			<xmin>413</xmin>
			<ymin>328</ymin>
			<xmax>449</xmax>
			<ymax>368</ymax>
		</bndbox>
	</object>
	<object>
		<name>F</name>
		<pose>Unspecified</pose>
		<truncated>0</truncated>
		<difficult>0</difficult>
		<bndbox>
			<xmin>450</xmin>
			<ymin>329</ymin>
			<xmax>486</xmax>
			<ymax>365</ymax>
		</bndbox>
	</object>
	<object>
		<name>F</name>
		<pose>Unspecified</pose>
		<truncated>0</truncated>
		<difficult>0</difficult>
		<bndbox>
			<xmin>47</xmin>
			<ymin>116</ymin>
			<xmax>94</xmax>
			<ymax>165</ymax>
		</bndbox>
	</object>
	<object>
		<name>F</name>
		<pose>Unspecified</pose>
		<truncated>0</truncated>
		<difficult>0</difficult>
		<bndbox>
			<xmin>39</xmin>
			<ymin>190</ymin>
			<xmax>69</xmax>
			<ymax>223</ymax>
		</bndbox>
	</object>
	<object>
		<name>F</name>
		<pose>Unspecified</pose>
		<truncated>0</truncated>
		<difficult>0</difficult>
		<bndbox>
			<xmin>185</xmin>
			<ymin>679</ymin>
			<xmax>216</xmax>
			<ymax>709</ymax>
		</bndbox>
	</object>
	<object>
		<name>F</name>
		<pose>Unspecified</pose>
		<truncated>0</truncated>
		<difficult>0</difficult>
		<bndbox>
			<xmin>263</xmin>
			<ymin>674</ymin>
			<xmax>292</xmax>
			<ymax>706</ymax>
		</bndbox>
	</object>
	<object>
		<name>F</name>
		<pose>Unspecified</pose>
		<truncated>0</truncated>
		<difficult>0</difficult>
		<bndbox>
			<xmin>341</xmin>
			<ymin>673</ymin>
			<xmax>370</xmax>
			<ymax>705</ymax>
		</bndbox>
	</object>
	<object>
		<name>F</name>
		<pose>Unspecified</pose>
		<truncated>0</truncated>
		<difficult>0</difficult>
		<bndbox>
			<xmin>456</xmin>
			<ymin>667</ymin>
			<xmax>485</xmax>
			<ymax>701</ymax>
		</bndbox>
	</object>
	<object>
		<name>F</name>
		<pose>Unspecified</pose>
		<truncated>0</truncated>
		<difficult>0</difficult>
		<bndbox>
			<xmin>643</xmin>
			<ymin>622</ymin>
			<xmax>673</xmax>
			<ymax>652</ymax>
		</bndbox>
	</object>
</annotation>
