<annotation>
	<folder>Img_cap_aume</folder>
	<filename>1325.jpg</filename>
	<path>C:\labelm\Retinanet_tutorial\Img_cap_aume\1325.jpg</path>
	<source>
		<database>Unknown</database>
	</source>
	<size>
		<width>720</width>
		<height>720</height>
		<depth>3</depth>
	</size>
	<segmented>0</segmented>
	<object>
		<name>P</name>
		<pose>Unspecified</pose>
		<truncated>0</truncated>
		<difficult>0</difficult>
		<bndbox>
			<xmin>461</xmin>
			<ymin>49</ymin>
			<xmax>547</xmax>
			<ymax>94</ymax>
		</bndbox>
	</object>
	<object>
		<name>P</name>
		<pose>Unspecified</pose>
		<truncated>0</truncated>
		<difficult>0</difficult>
		<bndbox>
			<xmin>347</xmin>
			<ymin>95</ymin>
			<xmax>436</xmax>
			<ymax>140</ymax>
		</bndbox>
	</object>
	<object>
		<name>P</name>
		<pose>Unspecified</pose>
		<truncated>0</truncated>
		<difficult>0</difficult>
		<bndbox>
			<xmin>186</xmin>
			<ymin>29</ymin>
			<xmax>278</xmax>
			<ymax>82</ymax>
		</bndbox>
	</object>
	<object>
		<name>P</name>
		<pose>Unspecified</pose>
		<truncated>0</truncated>
		<difficult>0</difficult>
		<bndbox>
			<xmin>115</xmin>
			<ymin>554</ymin>
			<xmax>157</xmax>
			<ymax>656</ymax>
		</bndbox>
	</object>
	<object>
		<name>F</name>
		<pose>Unspecified</pose>
		<truncated>0</truncated>
		<difficult>0</difficult>
		<bndbox>
			<xmin>504</xmin>
			<ymin>106</ymin>
			<xmax>547</xmax>
			<ymax>147</ymax>
		</bndbox>
	</object>
	<object>
		<name>F</name>
		<pose>Unspecified</pose>
		<truncated>0</truncated>
		<difficult>0</difficult>
		<bndbox>
			<xmin>284</xmin>
			<ymin>86</ymin>
			<xmax>330</xmax>
			<ymax>140</ymax>
		</bndbox>
	</object>
</annotation>
