<annotation>
	<folder>Img_cap_aume</folder>
	<filename>1376.jpg</filename>
	<path>C:\labelm\Retinanet_tutorial\Img_cap_aume\1376.jpg</path>
	<source>
		<database>Unknown</database>
	</source>
	<size>
		<width>720</width>
		<height>720</height>
		<depth>3</depth>
	</size>
	<segmented>0</segmented>
	<object>
		<name>P</name>
		<pose>Unspecified</pose>
		<truncated>0</truncated>
		<difficult>0</difficult>
		<bndbox>
			<xmin>41</xmin>
			<ymin>182</ymin>
			<xmax>93</xmax>
			<ymax>267</ymax>
		</bndbox>
	</object>
	<object>
		<name>P</name>
		<pose>Unspecified</pose>
		<truncated>0</truncated>
		<difficult>0</difficult>
		<bndbox>
			<xmin>101</xmin>
			<ymin>346</ymin>
			<xmax>139</xmax>
			<ymax>433</ymax>
		</bndbox>
	</object>
	<object>
		<name>P</name>
		<pose>Unspecified</pose>
		<truncated>0</truncated>
		<difficult>0</difficult>
		<bndbox>
			<xmin>45</xmin>
			<ymin>453</ymin>
			<xmax>85</xmax>
			<ymax>542</ymax>
		</bndbox>
	</object>
	<object>
		<name>P</name>
		<pose>Unspecified</pose>
		<truncated>0</truncated>
		<difficult>0</difficult>
		<bndbox>
			<xmin>581</xmin>
			<ymin>146</ymin>
			<xmax>676</xmax>
			<ymax>192</ymax>
		</bndbox>
	</object>
	<object>
		<name>F</name>
		<pose>Unspecified</pose>
		<truncated>0</truncated>
		<difficult>0</difficult>
		<bndbox>
			<xmin>99</xmin>
			<ymin>505</ymin>
			<xmax>140</xmax>
			<ymax>550</ymax>
		</bndbox>
	</object>
</annotation>
