<annotation>
	<folder>Img_cap_aume</folder>
	<filename>59.jpg</filename>
	<path>C:\labelm\Retinanet_tutorial\Img_cap_aume\59.jpg</path>
	<source>
		<database>Unknown</database>
	</source>
	<size>
		<width>720</width>
		<height>720</height>
		<depth>3</depth>
	</size>
	<segmented>0</segmented>
	<object>
		<name>P</name>
		<pose>Unspecified</pose>
		<truncated>0</truncated>
		<difficult>0</difficult>
		<bndbox>
			<xmin>547</xmin>
			<ymin>306</ymin>
			<xmax>558</xmax>
			<ymax>330</ymax>
		</bndbox>
	</object>
	<object>
		<name>P</name>
		<pose>Unspecified</pose>
		<truncated>0</truncated>
		<difficult>0</difficult>
		<bndbox>
			<xmin>547</xmin>
			<ymin>360</ymin>
			<xmax>558</xmax>
			<ymax>383</ymax>
		</bndbox>
	</object>
	<object>
		<name>P</name>
		<pose>Unspecified</pose>
		<truncated>0</truncated>
		<difficult>0</difficult>
		<bndbox>
			<xmin>547</xmin>
			<ymin>399</ymin>
			<xmax>557</xmax>
			<ymax>423</ymax>
		</bndbox>
	</object>
	<object>
		<name>P</name>
		<pose>Unspecified</pose>
		<truncated>0</truncated>
		<difficult>0</difficult>
		<bndbox>
			<xmin>562</xmin>
			<ymin>464</ymin>
			<xmax>573</xmax>
			<ymax>489</ymax>
		</bndbox>
	</object>
	<object>
		<name>P</name>
		<pose>Unspecified</pose>
		<truncated>0</truncated>
		<difficult>0</difficult>
		<bndbox>
			<xmin>549</xmin>
			<ymin>495</ymin>
			<xmax>559</xmax>
			<ymax>517</ymax>
		</bndbox>
	</object>
	<object>
		<name>P</name>
		<pose>Unspecified</pose>
		<truncated>0</truncated>
		<difficult>0</difficult>
		<bndbox>
			<xmin>564</xmin>
			<ymin>534</ymin>
			<xmax>576</xmax>
			<ymax>557</ymax>
		</bndbox>
	</object>
	<object>
		<name>P</name>
		<pose>Unspecified</pose>
		<truncated>0</truncated>
		<difficult>0</difficult>
		<bndbox>
			<xmin>421</xmin>
			<ymin>300</ymin>
			<xmax>443</xmax>
			<ymax>312</ymax>
		</bndbox>
	</object>
	<object>
		<name>P</name>
		<pose>Unspecified</pose>
		<truncated>0</truncated>
		<difficult>0</difficult>
		<bndbox>
			<xmin>421</xmin>
			<ymin>346</ymin>
			<xmax>442</xmax>
			<ymax>360</ymax>
		</bndbox>
	</object>
	<object>
		<name>P</name>
		<pose>Unspecified</pose>
		<truncated>0</truncated>
		<difficult>0</difficult>
		<bndbox>
			<xmin>447</xmin>
			<ymin>361</ymin>
			<xmax>469</xmax>
			<ymax>374</ymax>
		</bndbox>
	</object>
	<object>
		<name>P</name>
		<pose>Unspecified</pose>
		<truncated>0</truncated>
		<difficult>0</difficult>
		<bndbox>
			<xmin>417</xmin>
			<ymin>560</ymin>
			<xmax>441</xmax>
			<ymax>574</ymax>
		</bndbox>
	</object>
	<object>
		<name>P</name>
		<pose>Unspecified</pose>
		<truncated>0</truncated>
		<difficult>0</difficult>
		<bndbox>
			<xmin>380</xmin>
			<ymin>560</ymin>
			<xmax>401</xmax>
			<ymax>574</ymax>
		</bndbox>
	</object>
	<object>
		<name>F</name>
		<pose>Unspecified</pose>
		<truncated>0</truncated>
		<difficult>0</difficult>
		<bndbox>
			<xmin>369</xmin>
			<ymin>156</ymin>
			<xmax>386</xmax>
			<ymax>173</ymax>
		</bndbox>
	</object>
	<object>
		<name>F</name>
		<pose>Unspecified</pose>
		<truncated>0</truncated>
		<difficult>0</difficult>
		<bndbox>
			<xmin>370</xmin>
			<ymin>263</ymin>
			<xmax>384</xmax>
			<ymax>280</ymax>
		</bndbox>
	</object>
	<object>
		<name>F</name>
		<pose>Unspecified</pose>
		<truncated>0</truncated>
		<difficult>0</difficult>
		<bndbox>
			<xmin>393</xmin>
			<ymin>258</ymin>
			<xmax>407</xmax>
			<ymax>275</ymax>
		</bndbox>
	</object>
	<object>
		<name>F</name>
		<pose>Unspecified</pose>
		<truncated>0</truncated>
		<difficult>0</difficult>
		<bndbox>
			<xmin>307</xmin>
			<ymin>154</ymin>
			<xmax>321</xmax>
			<ymax>168</ymax>
		</bndbox>
	</object>
	<object>
		<name>F</name>
		<pose>Unspecified</pose>
		<truncated>0</truncated>
		<difficult>0</difficult>
		<bndbox>
			<xmin>307</xmin>
			<ymin>180</ymin>
			<xmax>321</xmax>
			<ymax>195</ymax>
		</bndbox>
	</object>
	<object>
		<name>F</name>
		<pose>Unspecified</pose>
		<truncated>0</truncated>
		<difficult>0</difficult>
		<bndbox>
			<xmin>242</xmin>
			<ymin>146</ymin>
			<xmax>256</xmax>
			<ymax>160</ymax>
		</bndbox>
	</object>
	<object>
		<name>F</name>
		<pose>Unspecified</pose>
		<truncated>0</truncated>
		<difficult>0</difficult>
		<bndbox>
			<xmin>201</xmin>
			<ymin>150</ymin>
			<xmax>213</xmax>
			<ymax>163</ymax>
		</bndbox>
	</object>
	<object>
		<name>F</name>
		<pose>Unspecified</pose>
		<truncated>0</truncated>
		<difficult>0</difficult>
		<bndbox>
			<xmin>201</xmin>
			<ymin>203</ymin>
			<xmax>213</xmax>
			<ymax>219</ymax>
		</bndbox>
	</object>
	<object>
		<name>F</name>
		<pose>Unspecified</pose>
		<truncated>0</truncated>
		<difficult>0</difficult>
		<bndbox>
			<xmin>127</xmin>
			<ymin>148</ymin>
			<xmax>145</xmax>
			<ymax>168</ymax>
		</bndbox>
	</object>
	<object>
		<name>F</name>
		<pose>Unspecified</pose>
		<truncated>0</truncated>
		<difficult>0</difficult>
		<bndbox>
			<xmin>127</xmin>
			<ymin>204</ymin>
			<xmax>147</xmax>
			<ymax>224</ymax>
		</bndbox>
	</object>
	<object>
		<name>F</name>
		<pose>Unspecified</pose>
		<truncated>0</truncated>
		<difficult>0</difficult>
		<bndbox>
			<xmin>202</xmin>
			<ymin>258</ymin>
			<xmax>214</xmax>
			<ymax>272</ymax>
		</bndbox>
	</object>
	<object>
		<name>F</name>
		<pose>Unspecified</pose>
		<truncated>0</truncated>
		<difficult>0</difficult>
		<bndbox>
			<xmin>113</xmin>
			<ymin>297</ymin>
			<xmax>133</xmax>
			<ymax>316</ymax>
		</bndbox>
	</object>
	<object>
		<name>F</name>
		<pose>Unspecified</pose>
		<truncated>0</truncated>
		<difficult>0</difficult>
		<bndbox>
			<xmin>113</xmin>
			<ymin>324</ymin>
			<xmax>133</xmax>
			<ymax>343</ymax>
		</bndbox>
	</object>
	<object>
		<name>F</name>
		<pose>Unspecified</pose>
		<truncated>0</truncated>
		<difficult>0</difficult>
		<bndbox>
			<xmin>114</xmin>
			<ymin>351</ymin>
			<xmax>132</xmax>
			<ymax>369</ymax>
		</bndbox>
	</object>
	<object>
		<name>F</name>
		<pose>Unspecified</pose>
		<truncated>0</truncated>
		<difficult>0</difficult>
		<bndbox>
			<xmin>113</xmin>
			<ymin>378</ymin>
			<xmax>130</xmax>
			<ymax>395</ymax>
		</bndbox>
	</object>
	<object>
		<name>F</name>
		<pose>Unspecified</pose>
		<truncated>0</truncated>
		<difficult>0</difficult>
		<bndbox>
			<xmin>186</xmin>
			<ymin>349</ymin>
			<xmax>202</xmax>
			<ymax>363</ymax>
		</bndbox>
	</object>
	<object>
		<name>F</name>
		<pose>Unspecified</pose>
		<truncated>0</truncated>
		<difficult>0</difficult>
		<bndbox>
			<xmin>187</xmin>
			<ymin>374</ymin>
			<xmax>201</xmax>
			<ymax>391</ymax>
		</bndbox>
	</object>
	<object>
		<name>F</name>
		<pose>Unspecified</pose>
		<truncated>0</truncated>
		<difficult>0</difficult>
		<bndbox>
			<xmin>197</xmin>
			<ymin>418</ymin>
			<xmax>216</xmax>
			<ymax>439</ymax>
		</bndbox>
	</object>
	<object>
		<name>F</name>
		<pose>Unspecified</pose>
		<truncated>0</truncated>
		<difficult>0</difficult>
		<bndbox>
			<xmin>198</xmin>
			<ymin>460</ymin>
			<xmax>216</xmax>
			<ymax>480</ymax>
		</bndbox>
	</object>
	<object>
		<name>F</name>
		<pose>Unspecified</pose>
		<truncated>0</truncated>
		<difficult>0</difficult>
		<bndbox>
			<xmin>112</xmin>
			<ymin>445</ymin>
			<xmax>130</xmax>
			<ymax>463</ymax>
		</bndbox>
	</object>
	<object>
		<name>F</name>
		<pose>Unspecified</pose>
		<truncated>0</truncated>
		<difficult>0</difficult>
		<bndbox>
			<xmin>110</xmin>
			<ymin>472</ymin>
			<xmax>130</xmax>
			<ymax>491</ymax>
		</bndbox>
	</object>
	<object>
		<name>F</name>
		<pose>Unspecified</pose>
		<truncated>0</truncated>
		<difficult>0</difficult>
		<bndbox>
			<xmin>114</xmin>
			<ymin>603</ymin>
			<xmax>136</xmax>
			<ymax>628</ymax>
		</bndbox>
	</object>
	<object>
		<name>F</name>
		<pose>Unspecified</pose>
		<truncated>0</truncated>
		<difficult>0</difficult>
		<bndbox>
			<xmin>141</xmin>
			<ymin>603</ymin>
			<xmax>165</xmax>
			<ymax>627</ymax>
		</bndbox>
	</object>
	<object>
		<name>F</name>
		<pose>Unspecified</pose>
		<truncated>0</truncated>
		<difficult>0</difficult>
		<bndbox>
			<xmin>170</xmin>
			<ymin>603</ymin>
			<xmax>192</xmax>
			<ymax>630</ymax>
		</bndbox>
	</object>
	<object>
		<name>F</name>
		<pose>Unspecified</pose>
		<truncated>0</truncated>
		<difficult>0</difficult>
		<bndbox>
			<xmin>263</xmin>
			<ymin>408</ymin>
			<xmax>277</xmax>
			<ymax>421</ymax>
		</bndbox>
	</object>
	<object>
		<name>F</name>
		<pose>Unspecified</pose>
		<truncated>0</truncated>
		<difficult>0</difficult>
		<bndbox>
			<xmin>441</xmin>
			<ymin>385</ymin>
			<xmax>456</xmax>
			<ymax>398</ymax>
		</bndbox>
	</object>
	<object>
		<name>F</name>
		<pose>Unspecified</pose>
		<truncated>0</truncated>
		<difficult>0</difficult>
		<bndbox>
			<xmin>442</xmin>
			<ymin>398</ymin>
			<xmax>456</xmax>
			<ymax>412</ymax>
		</bndbox>
	</object>
	<object>
		<name>F</name>
		<pose>Unspecified</pose>
		<truncated>0</truncated>
		<difficult>0</difficult>
		<bndbox>
			<xmin>262</xmin>
			<ymin>422</ymin>
			<xmax>276</xmax>
			<ymax>435</ymax>
		</bndbox>
	</object>
	<object>
		<name>F</name>
		<pose>Unspecified</pose>
		<truncated>0</truncated>
		<difficult>0</difficult>
		<bndbox>
			<xmin>263</xmin>
			<ymin>437</ymin>
			<xmax>276</xmax>
			<ymax>448</ymax>
		</bndbox>
	</object>
	<object>
		<name>F</name>
		<pose>Unspecified</pose>
		<truncated>0</truncated>
		<difficult>0</difficult>
		<bndbox>
			<xmin>263</xmin>
			<ymin>448</ymin>
			<xmax>276</xmax>
			<ymax>460</ymax>
		</bndbox>
	</object>
	<object>
		<name>F</name>
		<pose>Unspecified</pose>
		<truncated>0</truncated>
		<difficult>0</difficult>
		<bndbox>
			<xmin>219</xmin>
			<ymin>553</ymin>
			<xmax>236</xmax>
			<ymax>574</ymax>
		</bndbox>
	</object>
	<object>
		<name>F</name>
		<pose>Unspecified</pose>
		<truncated>0</truncated>
		<difficult>0</difficult>
		<bndbox>
			<xmin>349</xmin>
			<ymin>602</ymin>
			<xmax>372</xmax>
			<ymax>625</ymax>
		</bndbox>
	</object>
	<object>
		<name>F</name>
		<pose>Unspecified</pose>
		<truncated>0</truncated>
		<difficult>0</difficult>
		<bndbox>
			<xmin>376</xmin>
			<ymin>602</ymin>
			<xmax>399</xmax>
			<ymax>625</ymax>
		</bndbox>
	</object>
	<object>
		<name>F</name>
		<pose>Unspecified</pose>
		<truncated>0</truncated>
		<difficult>0</difficult>
		<bndbox>
			<xmin>404</xmin>
			<ymin>603</ymin>
			<xmax>424</xmax>
			<ymax>627</ymax>
		</bndbox>
	</object>
	<object>
		<name>F</name>
		<pose>Unspecified</pose>
		<truncated>0</truncated>
		<difficult>0</difficult>
		<bndbox>
			<xmin>470</xmin>
			<ymin>297</ymin>
			<xmax>484</xmax>
			<ymax>312</ymax>
		</bndbox>
	</object>
	<object>
		<name>F</name>
		<pose>Unspecified</pose>
		<truncated>0</truncated>
		<difficult>0</difficult>
		<bndbox>
			<xmin>471</xmin>
			<ymin>345</ymin>
			<xmax>484</xmax>
			<ymax>360</ymax>
		</bndbox>
	</object>
	<object>
		<name>F</name>
		<pose>Unspecified</pose>
		<truncated>0</truncated>
		<difficult>0</difficult>
		<bndbox>
			<xmin>419</xmin>
			<ymin>360</ymin>
			<xmax>431</xmax>
			<ymax>374</ymax>
		</bndbox>
	</object>
	<object>
		<name>F</name>
		<pose>Unspecified</pose>
		<truncated>0</truncated>
		<difficult>0</difficult>
		<bndbox>
			<xmin>559</xmin>
			<ymin>304</ymin>
			<xmax>572</xmax>
			<ymax>320</ymax>
		</bndbox>
	</object>
	<object>
		<name>F</name>
		<pose>Unspecified</pose>
		<truncated>0</truncated>
		<difficult>0</difficult>
		<bndbox>
			<xmin>559</xmin>
			<ymin>332</ymin>
			<xmax>573</xmax>
			<ymax>345</ymax>
		</bndbox>
	</object>
	<object>
		<name>F</name>
		<pose>Unspecified</pose>
		<truncated>0</truncated>
		<difficult>0</difficult>
		<bndbox>
			<xmin>559</xmin>
			<ymin>358</ymin>
			<xmax>572</xmax>
			<ymax>371</ymax>
		</bndbox>
	</object>
	<object>
		<name>F</name>
		<pose>Unspecified</pose>
		<truncated>0</truncated>
		<difficult>0</difficult>
		<bndbox>
			<xmin>559</xmin>
			<ymin>398</ymin>
			<xmax>575</xmax>
			<ymax>412</ymax>
		</bndbox>
	</object>
	<object>
		<name>F</name>
		<pose>Unspecified</pose>
		<truncated>0</truncated>
		<difficult>0</difficult>
		<bndbox>
			<xmin>545</xmin>
			<ymin>464</ymin>
			<xmax>560</xmax>
			<ymax>478</ymax>
		</bndbox>
	</object>
	<object>
		<name>F</name>
		<pose>Unspecified</pose>
		<truncated>0</truncated>
		<difficult>0</difficult>
		<bndbox>
			<xmin>547</xmin>
			<ymin>519</ymin>
			<xmax>560</xmax>
			<ymax>533</ymax>
		</bndbox>
	</object>
</annotation>
