<annotation>
	<folder>Img_cap_aume</folder>
	<filename>655.jpg</filename>
	<path>C:\labelm\Retinanet_tutorial\Img_cap_aume\655.jpg</path>
	<source>
		<database>Unknown</database>
	</source>
	<size>
		<width>720</width>
		<height>720</height>
		<depth>3</depth>
	</size>
	<segmented>0</segmented>
	<object>
		<name>F</name>
		<pose>Unspecified</pose>
		<truncated>0</truncated>
		<difficult>0</difficult>
		<bndbox>
			<xmin>527</xmin>
			<ymin>41</ymin>
			<xmax>562</xmax>
			<ymax>79</ymax>
		</bndbox>
	</object>
	<object>
		<name>F</name>
		<pose>Unspecified</pose>
		<truncated>0</truncated>
		<difficult>0</difficult>
		<bndbox>
			<xmin>592</xmin>
			<ymin>36</ymin>
			<xmax>626</xmax>
			<ymax>68</ymax>
		</bndbox>
	</object>
	<object>
		<name>F</name>
		<pose>Unspecified</pose>
		<truncated>0</truncated>
		<difficult>0</difficult>
		<bndbox>
			<xmin>666</xmin>
			<ymin>36</ymin>
			<xmax>702</xmax>
			<ymax>72</ymax>
		</bndbox>
	</object>
	<object>
		<name>F</name>
		<pose>Unspecified</pose>
		<truncated>0</truncated>
		<difficult>0</difficult>
		<bndbox>
			<xmin>114</xmin>
			<ymin>229</ymin>
			<xmax>139</xmax>
			<ymax>253</ymax>
		</bndbox>
	</object>
	<object>
		<name>F</name>
		<pose>Unspecified</pose>
		<truncated>0</truncated>
		<difficult>0</difficult>
		<bndbox>
			<xmin>150</xmin>
			<ymin>229</ymin>
			<xmax>176</xmax>
			<ymax>252</ymax>
		</bndbox>
	</object>
	<object>
		<name>F</name>
		<pose>Unspecified</pose>
		<truncated>0</truncated>
		<difficult>0</difficult>
		<bndbox>
			<xmin>187</xmin>
			<ymin>229</ymin>
			<xmax>212</xmax>
			<ymax>250</ymax>
		</bndbox>
	</object>
	<object>
		<name>F</name>
		<pose>Unspecified</pose>
		<truncated>0</truncated>
		<difficult>0</difficult>
		<bndbox>
			<xmin>224</xmin>
			<ymin>228</ymin>
			<xmax>247</xmax>
			<ymax>253</ymax>
		</bndbox>
	</object>
	<object>
		<name>F</name>
		<pose>Unspecified</pose>
		<truncated>0</truncated>
		<difficult>0</difficult>
		<bndbox>
			<xmin>252</xmin>
			<ymin>386</ymin>
			<xmax>296</xmax>
			<ymax>434</ymax>
		</bndbox>
	</object>
	<object>
		<name>F</name>
		<pose>Unspecified</pose>
		<truncated>0</truncated>
		<difficult>0</difficult>
		<bndbox>
			<xmin>139</xmin>
			<ymin>389</ymin>
			<xmax>185</xmax>
			<ymax>433</ymax>
		</bndbox>
	</object>
	<object>
		<name>F</name>
		<pose>Unspecified</pose>
		<truncated>0</truncated>
		<difficult>0</difficult>
		<bndbox>
			<xmin>17</xmin>
			<ymin>438</ymin>
			<xmax>52</xmax>
			<ymax>469</ymax>
		</bndbox>
	</object>
	<object>
		<name>F</name>
		<pose>Unspecified</pose>
		<truncated>0</truncated>
		<difficult>0</difficult>
		<bndbox>
			<xmin>27</xmin>
			<ymin>618</ymin>
			<xmax>70</xmax>
			<ymax>661</ymax>
		</bndbox>
	</object>
	<object>
		<name>F</name>
		<pose>Unspecified</pose>
		<truncated>0</truncated>
		<difficult>0</difficult>
		<bndbox>
			<xmin>210</xmin>
			<ymin>615</ymin>
			<xmax>250</xmax>
			<ymax>658</ymax>
		</bndbox>
	</object>
	<object>
		<name>F</name>
		<pose>Unspecified</pose>
		<truncated>0</truncated>
		<difficult>0</difficult>
		<bndbox>
			<xmin>284</xmin>
			<ymin>615</ymin>
			<xmax>324</xmax>
			<ymax>657</ymax>
		</bndbox>
	</object>
	<object>
		<name>F</name>
		<pose>Unspecified</pose>
		<truncated>0</truncated>
		<difficult>0</difficult>
		<bndbox>
			<xmin>406</xmin>
			<ymin>506</ymin>
			<xmax>441</xmax>
			<ymax>543</ymax>
		</bndbox>
	</object>
	<object>
		<name>F</name>
		<pose>Unspecified</pose>
		<truncated>0</truncated>
		<difficult>0</difficult>
		<bndbox>
			<xmin>500</xmin>
			<ymin>609</ymin>
			<xmax>541</xmax>
			<ymax>658</ymax>
		</bndbox>
	</object>
	<object>
		<name>F</name>
		<pose>Unspecified</pose>
		<truncated>0</truncated>
		<difficult>0</difficult>
		<bndbox>
			<xmin>635</xmin>
			<ymin>435</ymin>
			<xmax>686</xmax>
			<ymax>487</ymax>
		</bndbox>
	</object>
	<object>
		<name>F</name>
		<pose>Unspecified</pose>
		<truncated>0</truncated>
		<difficult>0</difficult>
		<bndbox>
			<xmin>635</xmin>
			<ymin>509</ymin>
			<xmax>687</xmax>
			<ymax>559</ymax>
		</bndbox>
	</object>
	<object>
		<name>F</name>
		<pose>Unspecified</pose>
		<truncated>0</truncated>
		<difficult>0</difficult>
		<bndbox>
			<xmin>634</xmin>
			<ymin>576</ymin>
			<xmax>684</xmax>
			<ymax>627</ymax>
		</bndbox>
	</object>
</annotation>
